Opencl20YigoujisuanZhongwenDisanban/README.md
Opencl20YigoujisuanZhongwenDisanban/__init__.py
Opencl20YigoujisuanZhongwenDisanban/__main__.py
Opencl20YigoujisuanZhongwenDisanban/file.epub
Opencl20YigoujisuanZhongwenDisanban/index.html
Opencl20YigoujisuanZhongwenDisanban/css/__init__.py
Opencl20YigoujisuanZhongwenDisanban/css/annotations.css
Opencl20YigoujisuanZhongwenDisanban/css/main.css
Opencl20YigoujisuanZhongwenDisanban/css/normalize.css
Opencl20YigoujisuanZhongwenDisanban/css/popup.css
Opencl20YigoujisuanZhongwenDisanban/font/__init__.py
Opencl20YigoujisuanZhongwenDisanban/font/fontello.eot
Opencl20YigoujisuanZhongwenDisanban/font/fontello.svg
Opencl20YigoujisuanZhongwenDisanban/font/fontello.ttf
Opencl20YigoujisuanZhongwenDisanban/font/fontello.woff
Opencl20YigoujisuanZhongwenDisanban/img/__init__.py
Opencl20YigoujisuanZhongwenDisanban/img/annotator-glyph-sprite.png
Opencl20YigoujisuanZhongwenDisanban/img/annotator-icon-sprite.png
Opencl20YigoujisuanZhongwenDisanban/img/apple-touch-icon.png
Opencl20YigoujisuanZhongwenDisanban/img/cancelfullscreen.png
Opencl20YigoujisuanZhongwenDisanban/img/close.png
Opencl20YigoujisuanZhongwenDisanban/img/fullscreen.png
Opencl20YigoujisuanZhongwenDisanban/img/loader.gif
Opencl20YigoujisuanZhongwenDisanban/img/menu-icon.png
Opencl20YigoujisuanZhongwenDisanban/img/save.png
Opencl20YigoujisuanZhongwenDisanban/img/saved.png
Opencl20YigoujisuanZhongwenDisanban/img/settings-s.png
Opencl20YigoujisuanZhongwenDisanban/img/settings.png
Opencl20YigoujisuanZhongwenDisanban/img/star.png
Opencl20YigoujisuanZhongwenDisanban/js/__init__.py
Opencl20YigoujisuanZhongwenDisanban/js/epub.js
Opencl20YigoujisuanZhongwenDisanban/js/epub.min.js
Opencl20YigoujisuanZhongwenDisanban/js/epub.min.map
Opencl20YigoujisuanZhongwenDisanban/js/hooks.min.js
Opencl20YigoujisuanZhongwenDisanban/js/hooks.min.map
Opencl20YigoujisuanZhongwenDisanban/js/reader.js
Opencl20YigoujisuanZhongwenDisanban/js/reader.js.map
Opencl20YigoujisuanZhongwenDisanban/js/reader.min.js
opencl_2_0_yigoujisuan_zhongwen_disanban-2024.3.2.0.dist-info/METADATA
opencl_2_0_yigoujisuan_zhongwen_disanban-2024.3.2.0.dist-info/WHEEL
opencl_2_0_yigoujisuan_zhongwen_disanban-2024.3.2.0.dist-info/entry_points.txt
opencl_2_0_yigoujisuan_zhongwen_disanban-2024.3.2.0.dist-info/top_level.txt
opencl_2_0_yigoujisuan_zhongwen_disanban-2024.3.2.0.dist-info/RECORD
